[{"latlng":{"lat":38.90406185086871,"lng":80.33203125},"iconUrl":"./dist/static/img/mapicon/plane.png"},{"latlng":{"lat":40.59329811348891,"lng":83.67187500000001},"iconUrl":"./dist/static/img/mapicon/plane.png"},{"latlng":{"lat":41.65258828582167,"lng":89.73632812500001},"iconUrl":"./dist/static/img/mapicon/plane.png"},{"latlng":{"lat":41.65258828582167,"lng":97.20703125000001},"iconUrl":"./dist/static/img/mapicon/plane.png"},{"latlng":{"lat":38.76713738705545,"lng":105.64453125000001},"iconUrl":"./dist/static/img/mapicon/plane.png"},{"latlng":{"lat":35.83138697835907,"lng":108.45703125000001},"iconUrl":"./dist/static/img/mapicon/plane.png"},{"latlng":{"lat":35.04370362097513,"lng":111.79687500000001},"iconUrl":"./dist/static/img/mapicon/plane.png"},{"latlng":{"lat":35.04370362097513,"lng":119.26757812500001},"iconUrl":"./dist/static/img/mapicon/plane.png"},{"latlng":{"lat":33.151568333316725,"lng":119.97070312500001},"iconUrl":"./dist/static/img/mapicon/user.png"},{"latlng":{"lat":35.04370362097513,"lng":109.07226562500001},"iconUrl":"./dist/static/img/mapicon/train.png"},{"latlng":{"lat":35.04370362097513,"lng":109.07226562500001},"iconUrl":"./dist/static/img/mapicon/train.png"},{"latlng":{"lat":35.04370362097513,"lng":109.07226562500001},"iconUrl":"./dist/static/img/mapicon/train.png"},{"latlng":{"lat":35.04370362097513,"lng":109.07226562500001},"iconUrl":"./dist/static/img/mapicon/train.png"},{"latlng":{"lat":35.04370362097513,"lng":109.07226562500001},"iconUrl":"./dist/static/img/mapicon/train.png"},{"latlng":{"lat":35.04370362097513,"lng":109.07226562500001},"iconUrl":"./dist/static/img/mapicon/train.png"},{"latlng":{"lat":35.04370362097513,"lng":109.07226562500001},"iconUrl":"./dist/static/img/mapicon/train.png"},{"latlng":{"lat":35.04370362097513,"lng":109.07226562500001},"iconUrl":"./dist/static/img/mapicon/train.png"},{"latlng":{"lat":35.04370362097513,"lng":109.07226562500001},"iconUrl":"./dist/static/img/mapicon/train.png"},{"latlng":{"lat":41.0367470846022,"lng":95.62499865889549},"iconUrl":"./dist/static/img/mapicon/user.png"},{"latlng":{"lat":41.30139232737776,"lng":100.81054553389552},"iconUrl":"./dist/static/img/mapicon/user.png"},{"latlng":{"lat":41.958323283398435,"lng":107.84179553389549},"iconUrl":"./dist/static/img/mapicon/user.png"},{"latlng":{"lat":42.99546468299236,"lng":112.49999865889552},"iconUrl":"./dist/static/img/mapicon/user.png"},{"latlng":{"lat":44.393421003282974,"lng":115.92773303389549},"iconUrl":"./dist/static/img/mapicon/user.png"},{"latlng":{"lat":46.12546880438215,"lng":118.38867053389549},"iconUrl":"./dist/static/img/mapicon/user.png"},{"latlng":{"lat":48.508286918412495,"lng":121.28906115889549},"iconUrl":"./dist/static/img/mapicon/user.png"},{"latlng":{"lat":43.63493953429603,"lng":120.58593615889552},"iconUrl":"./dist/static/img/mapicon/user.png"},{"latlng":{"lat":39.1544056557421,"lng":92.72460803389549},"iconUrl":"./dist/static/img/mapicon/user.png"},{"latlng":{"lat":38.33180798633983,"lng":89.91210803389552},"iconUrl":"./dist/static/img/mapicon/user.png"},{"latlng":{"lat":37.778158389076424,"lng":86.74804553389552},"iconUrl":"./dist/static/img/mapicon/user.png"},{"latlng":{"lat":36.939857317086606,"lng":83.6718736588955},"iconUrl":"./dist/static/img/mapicon/user.png"}]